iweb
