Metadata-Version: 1.1
Name: iweb
Version: 0.0.13
Summary: iweb is a framework for developing Model View Controller (MVC).
Home-page: https://github.com/chaluemwut/iweb.git
Author: Chaluemwut Noyunsan
Author-email: UNKNOWN
License: UNKNOWN
Download-URL: https://github.com/chaluemwut/iweb.git
Platform: UNKNOWN
